raiden_client/__init__.py
raiden_client/exceptions.py
raiden_client/raiden_api.py
raiden_client/types.py
raiden_client/utils.py
raiden_client/endpoints/__init__.py
raiden_client/endpoints/address.py
raiden_client/endpoints/channel.py
raiden_client/endpoints/channel_close.py
raiden_client/endpoints/channel_deposit.py
raiden_client/endpoints/channel_open.py
raiden_client/endpoints/channel_withdraw.py
raiden_client/endpoints/channels.py
raiden_client/endpoints/connection_disconnect.py
raiden_client/endpoints/connections.py
raiden_client/endpoints/connections_connect.py
raiden_client/endpoints/mint_tokens.py
raiden_client/endpoints/non_settled_partners.py
raiden_client/endpoints/payment.py
raiden_client/endpoints/payment_events.py
raiden_client/endpoints/pending_transfers.py
raiden_client/endpoints/token_registry.py
raiden_client/endpoints/tokens.py
raiden_client/interfaces/__init__.py
raiden_client/interfaces/cli.py
raiden_client/interfaces/client.py
raiden_client/interfaces/cli_commands/__init__.py
raiden_client/interfaces/cli_commands/address.py
raiden_client/interfaces/cli_commands/channel.py
raiden_client/interfaces/cli_commands/channel_close.py
raiden_client/interfaces/cli_commands/channel_deposit.py
raiden_client/interfaces/cli_commands/channel_open.py
raiden_client/interfaces/cli_commands/channel_withdraw.py
raiden_client/interfaces/cli_commands/channels.py
raiden_client/interfaces/cli_commands/connection_disconnect.py
raiden_client/interfaces/cli_commands/connections.py
raiden_client/interfaces/cli_commands/connections_connect.py
raiden_client/interfaces/cli_commands/mint_tokens.py
raiden_client/interfaces/cli_commands/non_settled_partners.py
raiden_client/interfaces/cli_commands/payment.py
raiden_client/interfaces/cli_commands/payment_events.py
raiden_client/interfaces/cli_commands/pending_transfers.py
raiden_client/interfaces/cli_commands/token_registry.py
raiden_client/interfaces/cli_commands/tokens.py
raiden_client-1.0.0.dist-info/LICENSE
raiden_client-1.0.0.dist-info/METADATA
raiden_client-1.0.0.dist-info/WHEEL
raiden_client-1.0.0.dist-info/entry_points.txt
raiden_client-1.0.0.dist-info/top_level.txt
raiden_client-1.0.0.dist-info/RECORD
