Metadata-Version: 2.1
Name: raiden-client
Version: 1.0.0
Summary: Client library for Raiden Rest API
Home-page: https://github.com/maddevsio/raiden-python-client
Author: Aleksandr Sobolev
Author-email: thesobolev@gmail.com
License: MIT license
Keywords: raiden
Platform: UNKNOWN
Classifier: Development Status :: 4 - Beta
Classifier: Environment :: Console
Classifier: Intended Audience :: Developers
Classifier: License :: OSI Approved :: MIT License
Classifier: Programming Language :: Python :: 3 :: Only
Classifier: Programming Language :: Python :: 3.5
Classifier: Programming Language :: Python :: 3.6
Classifier: Programming Language :: Python :: 3.7
Requires-Dist: requests (<2.23.0,>=2.22.0)
Requires-Dist: mypy-extensions (<0.5.0,>=0.4.1)
Requires-Dist: eth-hash[pycryptodome] (<0.3.0,>=0.2.0)
Requires-Dist: argcomplete (<2,>=1.10.0)
Requires-Dist: web3 (==4.9.1)
Provides-Extra: dev
Requires-Dist: black (<19.4,>=19.3b0) ; extra == 'dev'
Requires-Dist: codecov (<2.1.0,>=2.0.15) ; extra == 'dev'
Requires-Dist: pytest (<4.7.0,>=4.6.3) ; extra == 'dev'
Requires-Dist: pytest-cov (<2.8.0,>=2.7.1) ; extra == 'dev'
Requires-Dist: pytest-mypy (<0.4.0,>=0.3.3) ; extra == 'dev'
Provides-Extra: docs
Requires-Dist: requests (<2.23.0,>=2.22.0) ; extra == 'docs'
Requires-Dist: mypy-extensions (<0.5.0,>=0.4.1) ; extra == 'docs'
Requires-Dist: eth-hash[pycryptodome] (<0.3.0,>=0.2.0) ; extra == 'docs'
Requires-Dist: argcomplete (<2,>=1.10.0) ; extra == 'docs'
Requires-Dist: web3 (==4.9.1) ; extra == 'docs'
Requires-Dist: sphinx-argparse (<0.3.0,>=0.2.5) ; extra == 'docs'
Requires-Dist: sphinx-autodoc-typehints (<1.8.0,>=1.7.0) ; extra == 'docs'
Provides-Extra: raiden
Requires-Dist: requests (<2.23.0,>=2.22.0) ; extra == 'raiden'
Requires-Dist: mypy-extensions (<0.5.0,>=0.4.1) ; extra == 'raiden'
Requires-Dist: eth-hash[pycryptodome] (<0.3.0,>=0.2.0) ; extra == 'raiden'
Requires-Dist: argcomplete (<2,>=1.10.0) ; extra == 'raiden'
Requires-Dist: web3 (==4.9.1) ; extra == 'raiden'
